Demux1to8/DM1to8.v
module demux1to8 (
    input D,
    input [2:0] S,
    output reg [7:0] Y
);

always @(*) begin
    Y = 8'b0;
    Y[S] = D;
end
// Cách làm khác:
/*  always @(*) begin
        // Default tất cả output = 0
        Y = 8'b0;

        case ({S2, S1, S0})
            3'b000: Y[0] = D;
            3'b001: Y[1] = D;
            3'b010: Y[2] = D;
            3'b011: Y[3] = D;
            3'b100: Y[4] = D;
            3'b101: Y[5] = D;
            3'b110: Y[6] = D;
            3'b111: Y[7] = D;
        endcase
*/    
endmodule

Chapter_4/Demux1to8/DM1to8_tb.v
`include "DM1to8.v"

module demux1to8_tb;
    reg D;
    reg [2:0] S;
    wire [7:0] Y;

demux1to8 test (D,S,Y);
integer i;
initial begin
    $dumpfile ("DM1to8.vcd");
    $dumpvars (0,demux1to8_tb);
     D = 1;
        for (i = 0; i < 8; i = i + 1) begin
            S = i; #10;
        end
    $finish;
end
endmodule

Demux1to8/DM1to8.vcd
$date
	Fri May 29 23:20:18 2026
$end
$version
	Icarus Verilog
$end
$timescale
	1s
$end
$scope module demux1to8_tb $end
$var wire 8 ! Y [7:0] $end
$var reg 1 " D $end
$var reg 3 # S [2:0] $end
$var integer 32 $ i [31:0] $end
$scope module test $end
$var wire 1 " D $end
$var wire 3 % S [2:0] $end
$var reg 8 & Y [7:0] $end
$upscope $end
$upscope $end
$enddefinitions $end
#0
$dumpvars
b1 &
b0 %
b0 $
b0 #
1"
b1 !
$end
#10
b10 !
b10 &
b1 #
b1 %
b1 $
#20
b100 !
b100 &
b10 #
b10 %
b10 $
#30
b1000 !
b1000 &
b11 #
b11 %
b11 $
#40
b10000 !
b10000 &
b100 #
b100 %
b100 $
#50
b100000 !
b100000 &
b101 #
b101 %
b101 $
#60
b1000000 !
b1000000 &
b110 #
b110 %
b110 $
#70
b10000000 !
b10000000 &
b111 #
b111 %
b111 $
#80
b1000 $
