SPI_4_MODE/design.v
////////////////////////////////////////////////////////////////////////////////
// Module Name : spi_master
// Description : SPI Master hỗ trợ 4 mode (CPOL/CPHA) - chuẩn theo timing diagram
////////////////////////////////////////////////////////////////////////////////
module spi_master (
    input        clk,
    input        rst,
    input        start,
    input  [1:0] mode,      // {CPOL, CPHA}
    input  [7:0] data_in,
    output reg   mosi,
    output reg   sclk,
    output reg   cs,
    output reg   done
);

wire cpol = mode[1];
wire cpha = mode[0];

reg [2:0] bit_cnt;
reg [7:0] shift_reg;
reg [3:0] clk_div;
reg       busy;

// Chia clock: toggle SCLK mỗi 5 chu kỳ clk hệ thống
wire sclk_en = (clk_div == 4);

// Phát hiện cạnh dựa trên giá trị sclk TRƯỚC khi toggle:
//   Leading  edge: sclk đang ở idle (= cpol)  -> sắp chuyển sang active (~cpol)
//   Trailing edge: sclk đang ở active (~cpol) -> sắp chuyển về idle (cpol)
wire leading_edge  = sclk_en && busy && (sclk ==  cpol);
wire trailing_edge = sclk_en && busy && (sclk == ~cpol);

always @(posedge clk or posedge rst) begin
    if (rst) begin
        mosi      <= 0;
        sclk      <= 0;
        cs        <= 1;
        done      <= 0;
        bit_cnt   <= 0;
        shift_reg <= 0;
        clk_div   <= 0;
        busy      <= 0;
    end else begin
        done <= 0;

        // ----------------------------------------------------------------
        // Bắt đầu giao dịch
        // ----------------------------------------------------------------
        if (start && !busy) begin
            busy      <= 1;
            cs        <= 0;
            shift_reg <= data_in;
            bit_cnt   <= 0;
            clk_div   <= 0;
            sclk      <= cpol;       // SCLK về trạng thái idle đúng mode

            // CPHA=0: drive bit đầu tiên ngay khi CS xuống
            // (trước leading edge đầu tiên, đúng với Mode 0 và Mode 2)
            if (!cpha)
                mosi <= data_in[7];
        end

        // ----------------------------------------------------------------
        // Đang truyền
        // ----------------------------------------------------------------
        if (busy) begin
            clk_div <= clk_div + 1;

            // Toggle SCLK
            if (sclk_en) begin
                clk_div <= 0;
                sclk    <= ~sclk;
            end

            // ---- CPHA = 0 (Mode 0 & Mode 2) ----
            // Drive MOSI tại trailing edge -> chuẩn bị bit tiếp theo
            // Slave đã sample tại leading edge trước đó
            if (!cpha && trailing_edge) begin
                if (bit_cnt == 7) begin
                    // Đã truyền xong 8 bit
                    busy <= 0;
                    cs   <= 1;
                    done <= 1;
                end else begin
                    // Shift và drive bit tiếp theo
                    shift_reg <= {shift_reg[6:0], 1'b0};
                    mosi      <= shift_reg[6];
                end
                bit_cnt <= bit_cnt + 1;
            end

            // ---- CPHA = 1 (Mode 1 & Mode 3) ----
            // Drive MOSI tại leading edge
            // Slave sample tại trailing edge
            if (cpha && leading_edge) begin
                mosi      <= shift_reg[7];
                shift_reg <= {shift_reg[6:0], 1'b0};
                if (bit_cnt == 7) begin
                    busy <= 0;
                    cs   <= 1;
                    done <= 1;
                end
                bit_cnt <= bit_cnt + 1;
            end
        end

    end
end

endmodule

SPI_4_MODE/testbench.v
`timescale 1ns / 1ps
`include "design.v"

module spi_master_tb;
    reg        clk;
    reg        rst;
    reg        start;
    reg  [1:0] mode;
    reg  [7:0] data_in;

    wire       mosi;
    wire       sclk;
    wire       cs;
    wire       done;

    spi_master uut ( .clk(clk), .rst(rst), .start(start), .mode(mode), .data_in(data_in), .mosi(mosi), .sclk(sclk), .cs(cs), .done(done));

    initial clk = 0;
    always #5 clk = ~clk;

    initial begin
        $dumpfile("design.vcd");
        $dumpvars(0, spi_master_tb);

        rst     = 1; // Reset
        start   = 0;
        mode    = 2'b00;
        data_in = 8'h00;
        #40;
        rst = 0;      
        #40;

        //Mode 0 (CPOL=0, CPHA=0)
        mode    = 2'b00;
        data_in = 8'hA5;
        #40;
        start = 1; #10; start = 0;
        #1000;

        //Mode 1 (CPOL=0, CPHA=1)
        mode    = 2'b01;
        data_in = 8'h3C;
        #40;
        start = 1; #10; start = 0;
        #1000;

        //Mode 2 (CPOL=1, CPHA=0)
        mode    = 2'b10;
        data_in = 8'h69;
        #40;
        start = 1; #10; start = 0;
        #1000;

        //Mode 3 (CPOL=1, CPHA=1)
        mode    = 2'b11;
        data_in = 8'hF0;
        #40;
        start = 1; #10; start = 0;
        #1000;

        $finish;
    end

endmodule

SPI_4_MODE/design.vcd
$date
	Wed Jun 10 16:41:53 2026
$end
$version
	Icarus Verilog
$end
$timescale
	1ps
$end
$scope module spi_master_tb $end
$var wire 1 ! sclk $end
$var wire 1 " mosi $end
$var wire 1 # done $end
$var wire 1 $ cs $end
$var reg 1 % clk $end
$var reg 8 & data_in [7:0] $end
$var reg 2 ' mode [1:0] $end
$var reg 1 ( rst $end
$var reg 1 ) start $end
$scope module uut $end
$var wire 1 % clk $end
$var wire 8 * data_in [7:0] $end
$var wire 1 + leading_edge $end
$var wire 2 , mode [1:0] $end
$var wire 1 ( rst $end
$var wire 1 ) start $end
$var wire 1 - trailing_edge $end
$var wire 1 . sclk_en $end
$var wire 1 / cpol $end
$var wire 1 0 cpha $end
$var reg 3 1 bit_cnt [2:0] $end
$var reg 1 2 busy $end
$var reg 4 3 clk_div [3:0] $end
$var reg 1 $ cs $end
$var reg 1 # done $end
$var reg 1 " mosi $end
$var reg 1 ! sclk $end
$var reg 8 4 shift_reg [7:0] $end
$upscope $end
$upscope $end
$enddefinitions $end
#0
$dumpvars
b0 4
b0 3
02
b0 1
00
0/
0.
0-
b0 ,
0+
b0 *
0)
1(
b0 '
b0 &
0%
1$
0#
0"
0!
$end
#5000
1%
#10000
0%
#15000
1%
#20000
0%
#25000
1%
#30000
0%
#35000
1%
#40000
0%
0(
#45000
1%
#50000
0%
#55000
1%
#60000
0%
#65000
1%
#70000
0%
#75000
1%
#80000
0%
b10100101 &
b10100101 *
#85000
1%
#90000
0%
#95000
1%
#100000
0%
#105000
1%
#110000
0%
#115000
1%
#120000
0%
1)
#125000
1"
b10100101 4
0$
12
1%
#130000
0%
0)
#135000
b1 3
1%
#140000
0%
#145000
b10 3
1%
#150000
0%
#155000
b11 3
1%
#160000
0%
#165000
1+
1.
b100 3
1%
#170000
0%
#175000
0+
1!
0.
b0 3
1%
#180000
0%
#185000
b1 3
1%
#190000
0%
#195000
b10 3
1%
#200000
0%
#205000
b11 3
1%
#210000
0%
#215000
1-
1.
b100 3
1%
#220000
0%
#225000
0-
b1 1
0"
b1001010 4
0!
0.
b0 3
1%
#230000
0%
#235000
b1 3
1%
#240000
0%
#245000
b10 3
1%
#250000
0%
#255000
b11 3
1%
#260000
0%
#265000
1+
1.
b100 3
1%
#270000
0%
#275000
0+
1!
0.
b0 3
1%
#280000
0%
#285000
b1 3
1%
#290000
0%
#295000
b10 3
1%
#300000
0%
#305000
b11 3
1%
#310000
0%
#315000
1-
1.
b100 3
1%
#320000
0%
#325000
0-
b10 1
1"
b10010100 4
0!
0.
b0 3
1%
#330000
0%
#335000
b1 3
1%
#340000
0%
#345000
b10 3
1%
#350000
0%
#355000
b11 3
1%
#360000
0%
#365000
1+
1.
b100 3
1%
#370000
0%
#375000
0+
1!
0.
b0 3
1%
#380000
0%
#385000
b1 3
1%
#390000
0%
#395000
b10 3
1%
#400000
0%
#405000
b11 3
1%
#410000
0%
#415000
1-
1.
b100 3
1%
#420000
0%
#425000
0-
b11 1
0"
b101000 4
0!
0.
b0 3
1%
#430000
0%
#435000
b1 3
1%
#440000
0%
#445000
b10 3
1%
#450000
0%
#455000
b11 3
1%
#460000
0%
#465000
1+
1.
b100 3
1%
#470000
0%
#475000
0+
1!
0.
b0 3
1%
#480000
0%
#485000
b1 3
1%
#490000
0%
#495000
b10 3
1%
#500000
0%
#505000
b11 3
1%
#510000
0%
#515000
1-
1.
b100 3
1%
#520000
0%
#525000
0-
b100 1
b1010000 4
0!
0.
b0 3
1%
#530000
0%
#535000
b1 3
1%
#540000
0%
#545000
b10 3
1%
#550000
0%
#555000
b11 3
1%
#560000
0%
#565000
1+
1.
b100 3
1%
#570000
0%
#575000
0+
1!
0.
b0 3
1%
#580000
0%
#585000
b1 3
1%
#590000
0%
#595000
b10 3
1%
#600000
0%
#605000
b11 3
1%
#610000
0%
#615000
1-
1.
b100 3
1%
#620000
0%
#625000
0-
b101 1
1"
b10100000 4
0!
0.
b0 3
1%
#630000
0%
#635000
b1 3
1%
#640000
0%
#645000
b10 3
1%
#650000
0%
#655000
b11 3
1%
#660000
0%
#665000
1+
1.
b100 3
1%
#670000
0%
#675000
0+
1!
0.
b0 3
1%
#680000
0%
#685000
b1 3
1%
#690000
0%
#695000
b10 3
1%
#700000
0%
#705000
b11 3
1%
#710000
0%
#715000
1-
1.
b100 3
1%
#720000
0%
#725000
0-
b110 1
0"
b1000000 4
0!
0.
b0 3
1%
#730000
0%
#735000
b1 3
1%
#740000
0%
#745000
b10 3
1%
#750000
0%
#755000
b11 3
1%
#760000
0%
#765000
1+
1.
b100 3
1%
#770000
0%
#775000
0+
1!
0.
b0 3
1%
#780000
0%
#785000
b1 3
1%
#790000
0%
#795000
b10 3
1%
#800000
0%
#805000
b11 3
1%
#810000
0%
#815000
1-
1.
b100 3
1%
#820000
0%
#825000
0-
b111 1
1"
b10000000 4
0!
0.
b0 3
1%
#830000
0%
#835000
b1 3
1%
#840000
0%
#845000
b10 3
1%
#850000
0%
#855000
b11 3
1%
#860000
0%
#865000
1+
1.
b100 3
1%
#870000
0%
#875000
0+
1!
0.
b0 3
1%
#880000
0%
#885000
b1 3
1%
#890000
0%
#895000
b10 3
1%
#900000
0%
#905000
b11 3
1%
#910000
0%
#915000
1-
1.
b100 3
1%
#920000
0%
#925000
0-
b0 1
1#
1$
02
0!
0.
b0 3
1%
#930000
0%
#935000
0#
1%
#940000
0%
#945000
1%
#950000
0%
#955000
1%
#960000
0%
#965000
1%
#970000
0%
#975000
1%
#980000
0%
#985000
1%
#990000
0%
#995000
1%
#1000000
0%
#1005000
1%
#1010000
0%
#1015000
1%
#1020000
0%
#1025000
1%
#1030000
0%
#1035000
1%
#1040000
0%
#1045000
1%
#1050000
0%
#1055000
1%
#1060000
0%
#1065000
1%
#1070000
0%
#1075000
1%
#1080000
0%
#1085000
1%
#1090000
0%
#1095000
1%
#1100000
0%
#1105000
1%
#1110000
0%
#1115000
1%
#1120000
0%
#1125000
1%
#1130000
10
0%
b111100 &
b111100 *
b1 '
b1 ,
#1135000
1%
#1140000
0%
#1145000
1%
#1150000
0%
#1155000
1%
#1160000
0%
#1165000
1%
#1170000
0%
1)
#1175000
b111100 4
0$
12
1%
#1180000
0%
0)
#1185000
b1 3
1%
#1190000
0%
#1195000
b10 3
1%
#1200000
0%
#1205000
b11 3
1%
#1210000
0%
#1215000
1+
1.
b100 3
1%
#1220000
0%
#1225000
0+
b1 1
b1111000 4
0"
1!
0.
b0 3
1%
#1230000
0%
#1235000
b1 3
1%
#1240000
0%
#1245000
b10 3
1%
#1250000
0%
#1255000
b11 3
1%
#1260000
0%
#1265000
1-
1.
b100 3
1%
#1270000
0%
#1275000
0-
0!
0.
b0 3
1%
#1280000
0%
#1285000
b1 3
1%
#1290000
0%
#1295000
b10 3
1%
#1300000
0%
#1305000
b11 3
1%
#1310000
0%
#1315000
1+
1.
b100 3
1%
#1320000
0%
#1325000
0+
b10 1
b11110000 4
1!
0.
b0 3
1%
#1330000
0%
#1335000
b1 3
1%
#1340000
0%
#1345000
b10 3
1%
#1350000
0%
#1355000
b11 3
1%
#1360000
0%
#1365000
1-
1.
b100 3
1%
#1370000
0%
#1375000
0-
0!
0.
b0 3
1%
#1380000
0%
#1385000
b1 3
1%
#1390000
0%
#1395000
b10 3
1%
#1400000
0%
#1405000
b11 3
1%
#1410000
0%
#1415000
1+
1.
b100 3
1%
#1420000
0%
#1425000
0+
b11 1
b11100000 4
1"
1!
0.
b0 3
1%
#1430000
0%
#1435000
b1 3
1%
#1440000
0%
#1445000
b10 3
1%
#1450000
0%
#1455000
b11 3
1%
#1460000
0%
#1465000
1-
1.
b100 3
1%
#1470000
0%
#1475000
0-
0!
0.
b0 3
1%
#1480000
0%
#1485000
b1 3
1%
#1490000
0%
#1495000
b10 3
1%
#1500000
0%
#1505000
b11 3
1%
#1510000
0%
#1515000
1+
1.
b100 3
1%
#1520000
0%
#1525000
0+
b100 1
b11000000 4
1!
0.
b0 3
1%
#1530000
0%
#1535000
b1 3
1%
#1540000
0%
#1545000
b10 3
1%
#1550000
0%
#1555000
b11 3
1%
#1560000
0%
#1565000
1-
1.
b100 3
1%
#1570000
0%
#1575000
0-
0!
0.
b0 3
1%
#1580000
0%
#1585000
b1 3
1%
#1590000
0%
#1595000
b10 3
1%
#1600000
0%
#1605000
b11 3
1%
#1610000
0%
#1615000
1+
1.
b100 3
1%
#1620000
0%
#1625000
0+
b101 1
b10000000 4
1!
0.
b0 3
1%
#1630000
0%
#1635000
b1 3
1%
#1640000
0%
#1645000
b10 3
1%
#1650000
0%
#1655000
b11 3
1%
#1660000
0%
#1665000
1-
1.
b100 3
1%
#1670000
0%
#1675000
0-
0!
0.
b0 3
1%
#1680000
0%
#1685000
b1 3
1%
#1690000
0%
#1695000
b10 3
1%
#1700000
0%
#1705000
b11 3
1%
#1710000
0%
#1715000
1+
1.
b100 3
1%
#1720000
0%
#1725000
0+
b110 1
b0 4
1!
0.
b0 3
1%
#1730000
0%
#1735000
b1 3
1%
#1740000
0%
#1745000
b10 3
1%
#1750000
0%
#1755000
b11 3
1%
#1760000
0%
#1765000
1-
1.
b100 3
1%
#1770000
0%
#1775000
0-
0!
0.
b0 3
1%
#1780000
0%
#1785000
b1 3
1%
#1790000
0%
#1795000
b10 3
1%
#1800000
0%
#1805000
b11 3
1%
#1810000
0%
#1815000
1+
1.
b100 3
1%
#1820000
0%
#1825000
0+
b111 1
0"
1!
0.
b0 3
1%
#1830000
0%
#1835000
b1 3
1%
#1840000
0%
#1845000
b10 3
1%
#1850000
0%
#1855000
b11 3
1%
#1860000
0%
#1865000
1-
1.
b100 3
1%
#1870000
0%
#1875000
0-
0!
0.
b0 3
1%
#1880000
0%
#1885000
b1 3
1%
#1890000
0%
#1895000
b10 3
1%
#1900000
0%
#1905000
b11 3
1%
#1910000
0%
#1915000
1+
1.
b100 3
1%
#1920000
0%
#1925000
0+
b0 1
1#
1$
02
1!
0.
b0 3
1%
#1930000
0%
#1935000
0#
1%
