Chapter_5/RS_Latch/RS.v
module RS (
    input S,R,clk,
    output reg Q,
    output Qn
);
assign Qn = ~Q;
always @(*) begin
if (clk) begin
   case ({S,R})
    2'b00: Q=Q;
    2'b01: Q=0;
    2'b10: Q=1;
    2'b11: Q=1'bx; 
   endcase 
end
end

endmodule

RS_Latch/RS_tb.v
`timescale 1ns/1ps
`include "RS.v"

module RS_tb;
    reg S,R,clk;
    wire Q,Qn;

RS test (S,R,clk,Q,Qn);

initial clk = 0;
   always #5 clk = ~clk;
initial begin
    $dumpfile ("RS.vcd");
    $dumpvars (0,RS_tb);
        S=0; R=0; #10;
        S=0; R=1; #10;
        S=1; R=0; #10;
        S=0; R=0; #10;
        S=1; R=1; #10;
    $finish;
end

endmodule

RS_Latch/RS.vcd
$date
	Sat May 30 11:15:18 2026
$end
$version
	Icarus Verilog
$end
$timescale
	1ps
$end
$scope module RS_tb $end
$var wire 1 ! Qn $end
$var wire 1 " Q $end
$var reg 1 # R $end
$var reg 1 $ S $end
$var reg 1 % clk $end
$scope module test $end
$var wire 1 ! Qn $end
$var wire 1 # R $end
$var wire 1 $ S $end
$var wire 1 % clk $end
$var reg 1 " Q $end
$upscope $end
$upscope $end
$enddefinitions $end
#0
$dumpvars
0%
0$
0#
x"
x!
$end
#5000
1%
#10000
0%
1#
#15000
1!
0"
1%
#20000
0%
0#
1$
#25000
0!
1"
1%
#30000
0%
0$
#35000
1%
#40000
0%
1#
1$
#45000
x!
x"
1%
