Chapter_5/JK_FF/JK_FF.v
module JK_FF (
    input pre,clr,clk,
    input J,K,
    output reg Q, Qn
);

    always @(negedge clk, negedge pre, negedge clr) begin
        if (!pre && !clr) begin
                Q = 1;
                Qn = 1;
            end
        else if (!pre) begin Q=1; Qn=0; end
            else if (!clr) begin Q=0; Qn=1; end
                else begin
                    case ({J,K})
                        2'b00: begin Q=Q; Qn=Qn; end
                        2'b01: begin Q=0; Qn=1; end
                        2'b10: begin Q=1; Qn=0; end
                        2'b11: begin Q= ~Q; Qn= ~Qn; end
                    endcase
                end
    end
    
endmodule

Chapter_5/JK_FF/JK_FF_tb.v
`timescale 1ns/1ps
`include "JK_FF.v"

module JK_FF_tb;
    reg pre,clr,clk;
    reg J,K;
    wire Q,Qn;

JK_FF test (pre,clr,clk,J,K,Q,Qn);

initial clk=1;
    always #5 clk= ~clk;
initial begin
    $dumpfile ("JK_FF.vcd");
    $dumpvars (0,JK_FF_tb);
        pre=0; clr=0; J=0; K=0; #10;
        pre=0; clr=1; J=0; K=0; #10;
        pre=1; clr=0; J=0; K=0; #10;
        pre=1; clr=1; J=0; K=0; #10;
        pre=1; clr=1; J=0; K=1; #10;
        pre=1; clr=1; J=1; K=0; #10;
        pre=1; clr=1; J=1; K=1; #10;
    $finish;
    end

endmodule

JK_FF/JK_FF.vcd
$date
	Sat May 30 12:16:28 2026
$end
$version
	Icarus Verilog
$end
$timescale
	1ps
$end
$scope module JK_FF_tb $end
$var wire 1 ! Qn $end
$var wire 1 " Q $end
$var reg 1 # J $end
$var reg 1 $ K $end
$var reg 1 % clk $end
$var reg 1 & clr $end
$var reg 1 ' pre $end
$scope module test $end
$var wire 1 # J $end
$var wire 1 $ K $end
$var wire 1 % clk $end
$var wire 1 & clr $end
$var wire 1 ' pre $end
$var reg 1 " Q $end
$var reg 1 ! Qn $end
$upscope $end
$upscope $end
$enddefinitions $end
#0
$dumpvars
0'
0&
1%
0$
0#
1"
1!
$end
#5000
0%
#10000
1%
1&
#15000
0!
0%
#20000
1!
0"
1%
0&
1'
#25000
0%
#30000
1%
1&
#35000
0%
#40000
1%
1$
#45000
0%
#50000
1%
0$
1#
#55000
0!
1"
0%
#60000
1%
1$
#65000
1!
0"
0%
