Chapter_4/Decoder2to4_En/dec2to4_en.v
module dec2to4_en (
    input [1:0] w,
    input en,
    output reg [3:0] y
);

always @(*) begin
    y = 4'b0;
    if (en == 1) 
        y [w] = 1;
    else 
        y = 4'b0;

end
endmodule

Chapter_4/Decoder2to4_En/dec2to4_en_tb.v
`include "dec2to4_en.v"
`timescale 1ns/1ps

module dec2to4_en_tb;
    reg [1:0] w;
    reg en;
    wire [3:0] y;

dec2to4_en test (w,en,y);
integer i;
initial begin
    $dumpfile ("dec2to4_en_tb.vcd");
    $dumpvars (0,dec2to4_en_tb);
    // test en=1
    en = 1;
    for (i=0; i<4; i=i+1) begin
        w = i;
        #10;
    end
    // test en=0
    en = 0;
    for (i=0; i<4; i=i+1) begin
        w = i;
        #10;
    end
    $finish;
end

endmodule

Decoder2to4_En/dec2to4_en_tb.vcd
$date
	Sat May 30 09:27:30 2026
$end
$version
	Icarus Verilog
$end
$timescale
	1ps
$end
$scope module dec2to4_en_tb $end
$var wire 4 ! y [3:0] $end
$var reg 1 " en $end
$var reg 2 # w [1:0] $end
$var integer 32 $ i [31:0] $end
$scope module test $end
$var wire 1 " en $end
$var wire 2 % w [1:0] $end
$var reg 4 & y [3:0] $end
$upscope $end
$upscope $end
$enddefinitions $end
#0
$dumpvars
b1 &
b0 %
b0 $
b0 #
1"
b1 !
$end
#10000
b10 !
b10 &
b1 #
b1 %
b1 $
#20000
b100 !
b100 &
b10 #
b10 %
b10 $
#30000
b1000 !
b1000 &
b11 #
b11 %
b11 $
#40000
b0 !
b0 &
b0 #
b0 %
0"
b0 $
#50000
b1 #
b1 %
b1 $
#60000
b10 #
b10 %
b10 $
#70000
b11 #
b11 %
b11 $
#80000
b100 $
