Chapter_4/Mux2to1/multi.v
module multi (
    input w0,w1,s,
    output f
);


assign f = (~s & w0) | (s & w1);

endmodule

Mux2to1/multi_tb.v
`include "multi.v"
module multi_tb;
reg w0,w1,s;
wire f;

multi mux (.w0(w0), .w1(w1), .s(s), .f(f));
initial begin
    $dumpfile ("multi.vcd");
    $dumpvars(0,multi_tb);
    s=0; w0=0; w1=0; #10;  // f = 0
    s=0; w0=0; w1=1; #10;  // f = 0
    s=0; w0=1; w1=0; #10;  // f = 1
    s=0; w0=1; w1=1; #10;  // f = 1

    s=1; w0=0; w1=0; #10;  // f = 0
    s=1; w0=0; w1=1; #10;  // f = 1
    s=1; w0=1; w1=0; #10;  // f = 0
    s=1; w0=1; w1=1; #10;  // f = 1
    $finish;
end

endmodule

Chapter_4/Mux2to1/multi.vcd
$date
	Fri May 29 22:48:41 2026
$end
$version
	Icarus Verilog
$end
$timescale
	1s
$end
$scope module multi_tb $end
$var wire 1 ! f $end
$var reg 1 " s $end
$var reg 1 # w0 $end
$var reg 1 $ w1 $end
$scope module mux $end
$var wire 1 ! f $end
$var wire 1 " s $end
$var wire 1 # w0 $end
$var wire 1 $ w1 $end
$upscope $end
$upscope $end
$enddefinitions $end
#0
$dumpvars
0$
0#
0"
0!
$end
#10
1$
#20
1!
0$
1#
#30
1$
#40
0!
0$
0#
1"
#50
1!
1$
#60
0!
0$
1#
#70
1!
1$
